{
  "id": "62DuY2IVFyLaFZKXkORV",
  "slug": "koko-eating-bananas",
  "rank": 37,
  "title": "Koko Eating Bananas",
  "difficulty": "medium",
  "topics": [
    "Binary Search"
  ],
  "externalUrl": "https://www.leetcode.com/problems/koko-eating-bananas",
  "numViews": 516,
  "questionBody": "<p>Koko loves to eat bananas. There are <code>n</code> piles of bananas, the <code>i<sup>th</sup></code> pile has <code>piles[i]</code> bananas. The guards have gone and will come back in <code>h</code> hours.</p>\n\n<p>Koko can decide her bananas-per-hour eating speed of <code>k</code>. Each hour, she chooses some pile of bananas and eats <code>k</code> bananas from that pile. If the pile has less than <code>k</code> bananas, she eats all of them instead and will not eat any more bananas during this hour.</p>\n\n<p>Koko likes to eat slowly but still wants to finish eating all the bananas before the guards return.</p>\n\n<p>Return <em>the minimum integer</em> <code>k</code> <em>such that she can eat all the bananas within</em> <code>h</code> <em>hours</em>.</p>\n\n<p>&nbsp;</p>\n<p><strong class=\"example\">Example 1:</strong></p>\n\n<pre>\n<strong>Input:</strong> piles = [3,6,7,11], h = 8\n<strong>Output:</strong> 4\n</pre>\n\n<p><strong class=\"example\">Example 2:</strong></p>\n\n<pre>\n<strong>Input:</strong> piles = [30,11,23,4,20], h = 5\n<strong>Output:</strong> 30\n</pre>\n\n<p><strong class=\"example\">Example 3:</strong></p>\n\n<pre>\n<strong>Input:</strong> piles = [30,11,23,4,20], h = 6\n<strong>Output:</strong> 23\n</pre>\n\n<p>&nbsp;</p>\n<p><strong>Constraints:</strong></p>\n\n<ul>\n\t<li><code>1 &lt;= piles.length &lt;= 10<sup>4</sup></code></li>\n\t<li><code>piles.length &lt;= h &lt;= 10<sup>9</sup></code></li>\n\t<li><code>1 &lt;= piles[i] &lt;= 10<sup>9</sup></code></li>\n</ul>\n",
  "clarifyingQuestions": [
    "What are the upper and lower bounds for the values in the `piles` array, and for the number of hours `h`?",
    "Can `piles` be empty or null? What should I return in that case?",
    "Is it guaranteed that a valid `k` always exists that allows Koko to eat all bananas within `h` hours?",
    "If there are multiple possible values of `k` that satisfy the condition, should I return the absolute minimum, or is any valid `k` acceptable?",
    "Are the values in the `piles` array integers only, or could they be floating-point numbers?"
  ],
  "edgeCases": [
    {
      "edgeCase": "piles is null or empty",
      "handling": "Return 0 or throw an IllegalArgumentException as there are no bananas to eat, or return an impossible rate like Integer.MAX_VALUE indicating no solution."
    },
    {
      "edgeCase": "h is less than the number of piles",
      "handling": "Return -1 or Integer.MAX_VALUE, indicating that it is impossible to eat all bananas within the given time, since Koko can only eat from one pile per hour."
    },
    {
      "edgeCase": "piles contains only one pile",
      "handling": "Calculate the minimum k directly by dividing the number of bananas in the pile by h, ceiling the result, and return that."
    },
    {
      "edgeCase": "All piles have a small number of bananas (e.g., 1 or 2)",
      "handling": "The binary search will quickly converge to a rate of 1 or 2, handled correctly by the `hoursNeeded` calculation."
    },
    {
      "edgeCase": "One pile has a huge amount of bananas (potential for integer overflow in calculation of hours)",
      "handling": "Use long type for intermediate calculations of hours needed, especially when dividing pile size by rate."
    },
    {
      "edgeCase": "piles contains very large values leading to potential integer overflow when calculating hours",
      "handling": "Ensure calculations for total hours use long data type to prevent overflow and provide accurate results."
    },
    {
      "edgeCase": "h is a very large number (e.g., greater than the sum of the pile sizes)",
      "handling": "The binary search lower bound should be 1, and upper bound should be the max pile size; the binary search will converge to the smallest possible rate."
    },
    {
      "edgeCase": "All piles are the same size",
      "handling": "The binary search will efficiently converge to the correct rate, as the `hoursNeeded` calculation will be consistent across iterations."
    }
  ],
  "companies": [
    {
      "slug": "amazon",
      "name": "Amazon",
      "logo": "/logos/amazon.jpg"
    },
    {
      "slug": "google",
      "name": "Google",
      "logo": "/logos/google.jpg"
    },
    {
      "slug": "meta",
      "name": "Meta",
      "logo": "/logos/meta.jpg"
    },
    {
      "slug": "microsoft",
      "name": "Microsoft",
      "logo": "/logos/microsoft.jpg"
    },
    {
      "slug": "bloomberg-lp",
      "name": "Bloomberg",
      "logo": "/logos/bloomberg-lp.jpg"
    },
    {
      "slug": "apple",
      "name": "Apple",
      "logo": "/logos/apple.jpg"
    },
    {
      "slug": "uber",
      "name": "Uber",
      "logo": "/logos/uber.jpg"
    },
    {
      "slug": "tiktok",
      "name": "TikTok",
      "logo": "/logos/tiktok.png"
    },
    {
      "slug": "yahoo",
      "name": "Yahoo",
      "logo": "/logos/yahoo.jpg"
    },
    {
      "slug": "adobe",
      "name": "Adobe",
      "logo": "/logos/adobe.jpg"
    },
    {
      "slug": "citadel",
      "name": "Citadel",
      "logo": "/logos/citadel.jpg"
    },
    {
      "slug": "doordash",
      "name": "DoorDash",
      "logo": "/logos/doordash.png"
    },
    {
      "slug": "netflix",
      "name": "Netflix",
      "logo": "/logos/netflix.jpg"
    },
    {
      "slug": "ebay",
      "name": "eBay",
      "logo": "/logos/ebay.jpg"
    },
    {
      "slug": "walmart",
      "name": "Walmart",
      "logo": "/logos/walmart.jpg"
    },
    {
      "slug": "ripple",
      "name": "Ripple",
      "logo": "/logos/ripple.jpg"
    },
    {
      "slug": "oracle",
      "name": "Oracle",
      "logo": "/logos/oracle.jpg"
    },
    {
      "slug": "autodesk",
      "name": "Autodesk",
      "logo": "/logos/autodesk.jpg"
    },
    {
      "slug": "splunk",
      "name": "Splunk",
      "logo": "/logos/splunk.jpg"
    },
    {
      "slug": "phonepe",
      "name": "Phonepe",
      "logo": "/logos/phonepe.jpg"
    },
    {
      "slug": "linkedin",
      "name": "LinkedIn",
      "logo": "/logos/linkedin.png"
    },
    {
      "slug": "paypal",
      "name": "PayPal",
      "logo": "/logos/paypal.jpg"
    },
    {
      "slug": "flipkart",
      "name": "Flipkart",
      "logo": "/logos/flipkart.jpg"
    },
    {
      "slug": "salesforce",
      "name": "Salesforce",
      "logo": "/logos/salesforce.png"
    },
    {
      "slug": "nutanix",
      "name": "Nutanix",
      "logo": "/logos/nutanix.jpg"
    },
    {
      "slug": "atlassian",
      "name": "Atlassian",
      "logo": "/logos/atlassian.png"
    },
    {
      "slug": "de-shaw",
      "name": "De Shaw",
      "logo": "/logos/de-shaw.jpg"
    },
    {
      "slug": "okta",
      "name": "Okta",
      "logo": "/logos/okta.jpg"
    }
  ],
  "solutions": {
    "bruteForce": {
      "overview": "The goal is to find the slowest eating speed Koko needs to eat all the bananas within a set time. The brute force method involves trying every possible eating speed, one by one, starting from the slowest possible, until we find the smallest speed that works.",
      "steps": [
        "Start with the slowest possible eating speed: one banana per hour.",
        "Check if Koko can eat all the bananas within the given time using this speed.",
        "If she can, then remember this speed as a possible answer.",
        "If not, increase the eating speed by one (e.g., two bananas per hour).",
        "Keep checking if Koko can finish all the bananas within the time limit using this new speed.",
        "Repeat the process of increasing the eating speed and checking if it works.",
        "Continue until you find an eating speed that works within the time, and any slower speed does not. The current speed will be the solution."
      ],
      "bigO": {
        "runtimeValue": "O(n * m)",
        "runtimeExplanation": "The algorithm iterates through potential eating speeds, starting from 1.  Let n be the number of piles of bananas and let m be the maximum number of bananas in a single pile. The maximum possible eating speed needed is thus m. For each potential eating speed, it iterates through all n piles to calculate the total time needed to eat all the bananas at that speed. Therefore, the outer loop runs up to m times, and the inner loop to check each speed runs n times, making the time complexity O(n * m).",
        "spaceValue": "O(1)",
        "spaceExplanation": "The brute force algorithm described iteratively checks eating speeds, updating only a few variables like the current eating speed and a flag indicating whether the current speed is feasible. It doesn't utilize any auxiliary data structures (like arrays or hash maps) to store intermediate results or track visited states. Therefore, the space required remains constant irrespective of the number of banana piles. The auxiliary space complexity is O(1)."
      },
      "languages": [
        "Python",
        "JavaScript",
        "TypeScript",
        "Java",
        "C++",
        "C#",
        "Go",
        "Rust",
        "Kotlin",
        "Swift",
        "Ruby",
        "PHP"
      ],
      "code": {
        "Python": "def koko_eating_bananas_brute_force(piles, hours_allowed):\n\n    slowest_eating_speed = 1\n    while True:\n        total_hours_needed = 0\n\n        # Iterate through each pile of bananas\n        for pile in piles:\n            total_hours_needed += (pile + slowest_eating_speed - 1) // slowest_eating_speed\n\n        # Check if Koko can eat all bananas within the time limit\n        if total_hours_needed <= hours_allowed:\n            # If Koko can, then we return the eating speed, since we're checking from slowest to fastest\n            return slowest_eating_speed\n\n        # If Koko can't, increment the eating speed\n        slowest_eating_speed += 1",
        "JavaScript": "function kokoEatingBananasBruteForce(piles, hoursAllowed) {\n  let maxPileSize = 0;\n\n  for (let i = 0; i < piles.length; i++) {\n    maxPileSize = Math.max(maxPileSize, piles[i]);\n  }\n\n  let smallestSpeedThatWorks = maxPileSize; \n\n  for (let currentSpeed = 1; currentSpeed <= maxPileSize; currentSpeed++) {\n\n    let timeNeeded = 0;\n\n    for (let i = 0; i < piles.length; i++) {\n      timeNeeded += Math.ceil(piles[i] / currentSpeed);\n    }\n\n    // Check if the current speed allows Koko to eat all bananas in time.\n    if (timeNeeded <= hoursAllowed) {\n\n      //Update the smallest speed found so far\n      smallestSpeedThatWorks = currentSpeed;\n\n      // Once we find a speed that works, check if a smaller speed exists that also works\n      let canReduceSpeed = true;\n\n      for (let slowerSpeed = 1; slowerSpeed < currentSpeed; slowerSpeed++) {\n        let timeNeededSlowerSpeed = 0;\n\n        for (let i = 0; i < piles.length; i++) {\n          timeNeededSlowerSpeed += Math.ceil(piles[i] / slowerSpeed);\n        }\n\n        // If a slower speed works, then the current one is not the minimum.\n        if (timeNeededSlowerSpeed <= hoursAllowed) {\n          canReduceSpeed = false;\n          break;\n        }\n      }\n\n      //If no smaller speed works, return the current\n      if (canReduceSpeed) {\n        return currentSpeed;\n      }\n    }\n  }\n\n  return smallestSpeedThatWorks;\n}\n",
        "TypeScript": "function kokoEatingBananasBruteForce(piles: number[], allowedTime: number): number {\n  let eatingSpeed = 1;\n\n  while (true) {\n    let totalTimeNeeded = 0;\n\n    // Calculate total time needed for current speed\n    for (const pile of piles) {\n      totalTimeNeeded += Math.ceil(pile / eatingSpeed);\n    }\n\n    //Check if Koko can eat all piles in allowed time\n    if (totalTimeNeeded <= allowedTime) {\n\n      //When current speed works, it is the minimum speed\n      return eatingSpeed;\n    }\n\n    //If current speed does not work, increment the speed\n    eatingSpeed++;\n  }\n}",
        "Java": "public class Solution {\n\n    public int minEatingSpeed(int[] piles, int maxHours) {\n        int slowestSpeed = 1;\n        \n        while (true) {\n            // Check if Koko can eat all piles at this speed\n            if (canEatAllBananas(piles, maxHours, slowestSpeed)) {\n                return slowestSpeed;\n            }\n\n            // Increase the speed to test the next possible value\n            slowestSpeed++;\n        }\n    }\n\n    private boolean canEatAllBananas(int[] piles, int maxHours, int currentSpeed) {\n        int totalHours = 0;\n\n        for (int pile : piles) {\n            // Calculate hours needed for each pile at currentSpeed\n            totalHours += (pile + currentSpeed - 1) / currentSpeed;\n        }\n\n        // Return true if total hours is within limit, false otherwise\n        return totalHours <= maxHours;\n    }\n}\n",
        "C++": "#include <vector>\n\nusing namespace std;\n\nclass Solution {\npublic:\n    int minEatingSpeed(vector<int>& piles, int hourSum) {\n        int slowestPossibleSpeed = 1;\n\n        while (true) {\n            int hoursNeeded = 0;\n\n            //Calculate hours needed to eat all piles at current speed\n            for (int pile : piles) {\n                hoursNeeded += (pile + slowestPossibleSpeed - 1) / slowestPossibleSpeed;\n            }\n\n            // Check if the current speed is sufficient.\n            if (hoursNeeded <= hourSum) {\n                return slowestPossibleSpeed;\n            }\n\n            //Increment speed if not sufficient.\n            slowestPossibleSpeed++;\n        }\n    }\n};",
        "C#": "public class Solution\n{\n\n    public int MinEatingSpeed(int[] piles, int hoursAllowed)\n    {\n        int slowestPossibleSpeed = 1;\n\n        while (true)\n        {\n            // Check if Koko can eat all bananas at the current speed\n            if (CanEatAllBananas(piles, hoursAllowed, slowestPossibleSpeed))\n            {\n                return slowestPossibleSpeed;\n            }\n\n            // Increase speed if the current speed is not enough\n            slowestPossibleSpeed++;\n        }\n    }\n\n    private bool CanEatAllBananas(int[] piles, int hoursAllowed, int currentSpeed)\n    {\n        double totalHoursNeeded = 0;\n\n        // It is necessary to iterate through each pile.\n        foreach (int pile in piles)\n        {\n\n            totalHoursNeeded += Math.Ceiling((double)pile / currentSpeed);\n        }\n\n        //The hours must not exceed the time provided to return true.\n        if (totalHoursNeeded <= hoursAllowed)\n        {\n            return true;\n        }\n\n        // Return false when eating speed is too slow.\n        return false;\n    }\n}",
        "Go": "package main\n\nfunc kokoEatingBananasBruteForce(piles []int, hours int) int {\n\n\tmaxPileSize := 0\n\tfor _, pileSize := range piles {\n\t\tif pileSize > maxPileSize {\n\t\t\tmaxPileSize = pileSize\n\t\t}\n\t}\n\n\tfor bananasPerHour := 1; bananasPerHour <= maxPileSize; bananasPerHour++ {\n\t\ttotalHoursNeeded := 0\n\n\t\t// Calculate how many hours are needed at this bananasPerHour.\n\t\tfor _, pileSize := range piles {\n\t\t\ttotalHoursNeeded += (pileSize + bananasPerHour - 1) / bananasPerHour\n\t\t}\n\n\t\t// If eating at bananasPerHour speed is fast enough, return it.\n\t\tif totalHoursNeeded <= hours {\n\t\t\treturn bananasPerHour\n\t\t}\n\t}\n\n\treturn maxPileSize\n}\n",
        "Rust": "fn can_eat_all_bananas(piles: &Vec<i32>, hourly_rate: i32, allowed_time: i32) -> bool {\n    let mut total_time_needed: i32 = 0;\n    for &pile_size in piles {\n        total_time_needed += (pile_size as f64 / hourly_rate as f64).ceil() as i32;\n    }\n    total_time_needed <= allowed_time\n}\n\nfn koko_eating_bananas_brute_force(piles: Vec<i32>, allowed_time: i32) -> i32 {\n    let mut min_eating_speed: i32 = 1;\n\n    loop {\n        // We must check if we can eat all bananas at this speed\n        if can_eat_all_bananas(&piles, min_eating_speed, allowed_time) {\n\n            // This is a valid speed so return.\n            return min_eating_speed;\n        }\n        // Increase the eating speed to check the next one\n        min_eating_speed += 1;\n    }\n}\n",
        "Kotlin": "fun kokoEatingBananasBruteForce(piles: IntArray, hours: Int): Int {\n    var slowestEatingSpeedThatWorks = Int.MAX_VALUE\n\n    for (eatingSpeed in 1..piles.maxOrNull()!!) {\n        var timeToEatAllPiles = 0.0\n\n        // Calculate the time needed to eat all piles at the current speed\n        for (pileSize in piles) {\n            timeToEatAllPiles += Math.ceil(pileSize.toDouble() / eatingSpeed.toDouble())\n        }\n\n        // Check if the current eating speed allows Koko to finish in time\n        if (timeToEatAllPiles <= hours) {\n\n            //Check for even slower speed\n            if (eatingSpeed < slowestEatingSpeedThatWorks) {\n                slowestEatingSpeedThatWorks = eatingSpeed\n            }\n        }\n    }\n\n    return slowestEatingSpeedThatWorks\n}",
        "Swift": "func minEatingSpeedBruteForce(piles: [Int], hours: Int) -> Int {\n    // Initialize the minimum eating speed to 1. \n    var minimumRate = 1\n    \n    while true {\n        var totalHoursNeeded = 0\n\n        // Calculate the total hours needed to eat all piles at the current rate.\n        for pile in piles {\n            totalHoursNeeded += (pile + minimumRate - 1) / minimumRate\n        }\n\n        // Check if Koko can eat all bananas within the given hours.\n        if totalHoursNeeded <= hours {\n            return minimumRate\n        }\n\n        // Increase the eating speed if the current rate doesn't work\n        minimumRate += 1\n    }\n}\n",
        "Ruby": "def koko_eating_bananas_brute_force(piles, hours):\n    slowest_speed = 1\n    \n    while True:\n        time_taken = 0\n\n        # Calculate the total time taken to eat all piles at the current speed\n        for pile in piles:\n            time_taken += (pile.to_f / slowest_speed).ceil\n\n        # If Koko can eat all bananas within the given time, return the speed\n        if time_taken <= hours:\n            return slowest_speed\n\n        # If not, increase the eating speed and try again\n        slowest_speed += 1\n",
        "PHP": "<?php\nfunction kokoEatingBananasBruteForce(array $piles, int $hours):\nstring {\n    $maxPile = max($piles);\n    $slowestSpeed = 1;\n\n    while ($slowestSpeed <= $maxPile) {\n        $totalHoursNeeded = 0;\n\n        foreach ($piles as $pile) {\n            $totalHoursNeeded += ceil($pile / $slowestSpeed);\n        }\n\n        // If we can eat all bananas within the given time,\n        // we've found a valid speed.\n        if ($totalHoursNeeded <= $hours) {\n            return (string)$slowestSpeed;\n        }\n\n        $slowestSpeed++;\n    }\n\n    return (string)$maxPile;\n}\n?>"
      }
    },
    "optimal": {
      "overview": "The core idea is to use a process of elimination to find the best eating speed for Koko. Instead of trying every possible speed, we narrow down the possibilities by checking if a speed is too slow or too fast, using a method similar to guessing a number between 1 and 100.",
      "steps": [
        "Figure out the slowest and fastest possible eating speeds for Koko. The slowest is eating one banana per hour, and the fastest is eating all the bananas from the largest pile in one hour.",
        "Pick a speed in the middle of the slowest and fastest speeds to test. This is your 'guess'.",
        "Calculate how long it would take Koko to eat all the bananas at that speed.",
        "If it takes too long (more than the time given), that means the speed is too slow, so you need to consider only faster speeds in the next step.",
        "If it doesn't take too long, the speed might be okay, but maybe there's an even slower speed that works. So, consider only slower speeds in the next step.",
        "Repeat steps 2-5, each time narrowing down the range of possible speeds, until you find the slowest speed that allows Koko to eat all the bananas within the given time."
      ],
      "bigO": {
        "runtimeValue": "O(n log m)",
        "runtimeExplanation": "The algorithm uses binary search to find the optimal eating speed. The search space for the eating speed ranges from 1 to the maximum number of bananas in a pile, where 'm' represents the maximum number of bananas in any pile.  For each potential eating speed within the binary search, the algorithm iterates through the 'n' piles of bananas to calculate the total time it takes Koko to eat all the bananas. This iteration to calculate the time takes O(n) time. Since binary search takes O(log m) and within each check we take O(n) to calculate the time, the overall time complexity is O(n log m).",
        "spaceValue": "O(1)",
        "spaceExplanation": "The algorithm predominantly uses a binary search approach which primarily involves arithmetic calculations and comparisons using a few variables to store the low, high and mid values of the search space. These variables take up constant space. There is no auxiliary data structure (like an array or hash map) that scales with the input size (number of piles of bananas). Therefore, the auxiliary space complexity is constant."
      },
      "languages": [
        "Python",
        "JavaScript",
        "TypeScript",
        "Java",
        "C++",
        "C#",
        "Go",
        "Rust",
        "Kotlin",
        "Swift",
        "Ruby",
        "PHP"
      ],
      "code": {
        "Python": "def koko_eating_bananas(piles, hours_to_eat):    max_pile_size = max(piles)\n    left = 1\n    right = max_pile_size\n\n    while left < right:\n        eating_speed = (left + right) // 2\n\n        # Calculate how long it takes to eat all piles at this speed.\n        total_time_to_eat = 0\n        for pile_size in piles:\n            total_time_to_eat += (pile_size + eating_speed - 1) // eating_speed\n\n        # If it takes too long, the speed is too slow.\n        if total_time_to_eat > hours_to_eat:\n            left = eating_speed + 1\n\n        # The speed is fast enough, try a slower speed.\n        else:\n            right = eating_speed\n\n    # 'left' will be the minimum eating speed to finish in time.\n    return left",
        "JavaScript": "function minEatingSpeed(piles, hoursAllowed) {\n  let maxPileSize = Math.max(...piles);\n  let left = 1;\n  let right = maxPileSize;\n\n  while (left < right) {\n    let eatingSpeed = Math.floor((left + right) / 2);\n\n    // Check if the current eating speed is feasible\n    let timeNeeded = 0;\n    for (let pileSize of piles) {\n      timeNeeded += Math.ceil(pileSize / eatingSpeed);\n    }\n\n    // If it takes too long, we need a higher eating speed\n    if (timeNeeded > hoursAllowed) {\n      left = eatingSpeed + 1;\n    } else {\n      // It's fast enough, try a slower eating speed\n      right = eatingSpeed;\n    }\n  }\n\n  // 'left' is the minimum eating speed that works\n  return left;\n}\n",
        "TypeScript": "function kokoEatingBananas(piles: number[], hoursToFinish: number): number {\n  let maxPileSize = Math.max(...piles);\n  let left = 1;\n  let right = maxPileSize;\n\n  let optimalKEatingSpeed = maxPileSize;\n\n  while (left <= right) {\n    let currentKEatingSpeed = Math.floor((left + right) / 2);\n    let hoursNeeded = 0;\n\n    for (let pileSize of piles) {\n      hoursNeeded += Math.ceil(pileSize / currentKEatingSpeed);\n    }\n\n    // If the current speed is too slow.\n    if (hoursNeeded > hoursToFinish) {\n\n      left = currentKEatingSpeed + 1;\n    }\n\n    // If the current speed is feasible.\n    else {\n      // Store the current speed as a possible solution.\n      optimalKEatingSpeed = currentKEatingSpeed;\n\n      // Try a slower speed.\n      right = currentKEatingSpeed - 1;\n    }\n  }\n\n  return optimalKEatingSpeed;\n}",
        "Java": "public class Solution {\n\n    public int minEatingSpeed(int[] piles, int hoursAllotted) {\n        int maxPileSize = 0;\n        for (int pile : piles) {\n            maxPileSize = Math.max(maxPileSize, pile);\n        }\n\n        int left = 1;\n        int right = maxPileSize;\n        int optimalSpeed = maxPileSize;\n\n        while (left <= right) {\n            int currentSpeed = left + (right - left) / 2;\n            long timeTaken = 0;\n\n            for (int pile : piles) {\n                timeTaken += (pile + currentSpeed - 1) / currentSpeed;\n            }\n\n            // If we can eat all piles in time, try a slower speed\n            if (timeTaken <= hoursAllotted) {\n                optimalSpeed = currentSpeed;\n                right = currentSpeed - 1;\n            }\n\n            // Otherwise, we need to eat faster\n            else {\n                left = currentSpeed + 1;\n            }\n        }\n\n        return optimalSpeed;\n    }\n}\n",
        "C++": "#include <vector>\n\nusing namespace std;\n\nclass Solution {\npublic:\n    int minEatingSpeed(vector<int>& piles, int hoursAllowed) {\n        int maximumPileSize = 0;\n        for (int pileSize : piles) {\n            maximumPileSize = max(maximumPileSize, pileSize);\n        }\n\n        int left = 1;\n        int right = maximumPileSize;\n        int minimumRate = maximumPileSize;\n\n        while (left <= right) {\n            int currentRate = left + (right - left) / 2;\n\n            // Check if Koko can eat all bananas at currentRate\n            long long totalHours = 0;\n            for (int pileSize : piles) {\n                totalHours += (pileSize + currentRate - 1) / currentRate;\n            }\n\n            if (totalHours <= hoursAllowed) {\n\n                // It's possible, try to find a smaller rate\n                minimumRate = currentRate;\n                right = currentRate - 1;\n            }\n            \n            else {\n                // It's not possible, need a larger rate\n\n                //The rate is too slow, so we adjust the minimum bound.\n                left = currentRate + 1;\n            }\n        }\n        return minimumRate;\n    }\n};\n",
        "C#": "public class Solution {\n    public int MinEatingSpeed(int[] piles, int hours) {\n        int maxPile = 0;\n        foreach (int pile in piles)\n        {\n            maxPile = Math.Max(maxPile, pile);\n        }\n\n        int left = 1;\n        int right = maxPile;\n\n        while (left < right)\n        {\n            int mid = left + (right - left) / 2;\n            \n            //Determine if the current eating speed is feasible\n            if (CanEatAllBananas(piles, hours, mid))\n            {\n                //Try to find a smaller eating speed if possible\n                right = mid;\n            }\n            else\n            {\n                //Increase the eating speed since it's too slow\n                left = mid + 1;\n            }\n        }\n\n        return left;\n    }\n\n    private bool CanEatAllBananas(int[] piles, int hours, int eatingSpeed)\n    {\n        double totalHoursNeeded = 0;\n        foreach (int pile in piles)\n        {\n            totalHoursNeeded += Math.Ceiling((double)pile / eatingSpeed);\n        }\n\n        //check if time exceeds the limit\n        return totalHoursNeeded <= hours;\n    }\n}",
        "Go": "package main\n\nfunc kokoEatingBananas(piles []int, hours int) int {\n\tleft := 1\n\tright := 0\n\tfor _, pile := range piles {\n\t\tif pile > right {\n\t\t\tright = pile\n\t\t}\n\t}\n\n\tfor left < right {\n\t\tmiddle := left + (right-left)/2\n\n\t\ttimeNeeded := 0\n\t\tfor _, pile := range piles {\n\t\t\ttimeNeeded += (pile + middle - 1) / middle\n\t\t}\n\n\t\t// Check if current eating speed is too slow\n\t\tif timeNeeded > hours {\n\t\t\tleft = middle + 1\n\n\t\t} else {\n\t\t\t// Try to find even slower eating speed\n\t\t\tright = middle\n\t\t}\n\t}\n\treturn left\n}\n",
        "Rust": "fn koko_eating_bananas(piles: Vec<i32>, hour_allotted: i32) -> i32 {\n    let mut left_eating_speed: i32 = 1;\n    let mut right_eating_speed: i32 = *piles.iter().max().unwrap();\n\n    let mut optimal_eating_speed: i32 = right_eating_speed;\n\n    while left_eating_speed <= right_eating_speed {\n        let mid_eating_speed: i32 = left_eating_speed + (right_eating_speed - left_eating_speed) / 2;\n\n        // Calculate the time taken to eat all piles at mid_eating_speed\n        let mut hours_needed: i32 = 0;\n        for &pile_size in &piles {\n            hours_needed += (pile_size as f64 / mid_eating_speed as f64).ceil() as i32;\n        }\n\n        if hours_needed <= hour_allotted {\n            // Current speed is feasible, try lower speeds\n            optimal_eating_speed = mid_eating_speed;\n            right_eating_speed = mid_eating_speed - 1;\n        } else {\n            // Current speed is too slow, increase the eating speed\n            left_eating_speed = mid_eating_speed + 1;\n        }\n    }\n\n    optimal_eating_speed\n}\n",
        "Kotlin": "fun kokoEatingBananas(pileOfBananas: IntArray, allottedTime: Int): Int {\n    var left = 1\n    var right = pileOfBananas.maxOrNull() ?: 1\n\n    var slowestEatingSpeedThatWorks = right\n\n    while (left <= right) {\n        val mid = left + (right - left) / 2\n        val timeTaken = calculateTimeTaken(pileOfBananas, mid)\n\n        // If Koko can eat all bananas in the given time.\n        if (timeTaken <= allottedTime) {\n            slowestEatingSpeedThatWorks = mid\n\n            // Try a slower eating speed.\n            right = mid - 1\n        } else {\n            // Need to eat faster.\n            left = mid + 1\n        }\n    }\n\n    return slowestEatingSpeedThatWorks\n}\n\nprivate fun calculateTimeTaken(pileOfBananas: IntArray, eatingSpeed: Int): Long {\n    var totalTime: Long = 0\n\n    //Iterate through each pile of bananas and calculate time to eat it\n    for (pile in pileOfBananas) {\n        totalTime += (pile + eatingSpeed - 1) / eatingSpeed\n    }\n    return totalTime\n}",
        "Swift": "func minEatingSpeed(piles: [Int], hours: Int) -> Int {\n    var left = 1\n    var right = piles.max()! \n\n    var minimumRateThatWorks = right\n\n    while left <= right {\n        let averageRate = left + (right - left) / 2\n        var timeNeeded = 0\n\n        for pile in piles {\n            timeNeeded += (pile + averageRate - 1) / averageRate\n        }\n\n        // If the time is too much, we need to increase rate\n        if timeNeeded > hours {\n            left = averageRate + 1\n        } else {\n\n            // Found a working rate, try to minimize it\n            minimumRateThatWorks = averageRate\n            right = averageRate - 1\n        }\n    }\n\n    //Binary search to find minimum possible rate.\n    return minimumRateThatWorks\n}\n",
        "Ruby": "def koko_eating_bananas(piles, hours_to_finish):\n  left_speed = 1\n  right_speed = piles.max\n\n  eating_speed_result = right_speed\n\n  while left_speed <= right_speed:\n    eating_speed_mid = left_speed + (right_speed - left_speed) / 2\n    eating_speed_mid = eating_speed_mid.to_i\n\n    hours_needed = 0\n    for pile in piles:\n      hours_needed += (pile.to_f / eating_speed_mid).ceil\n\n    # Need to increase eating speed\n    if hours_needed <= hours_to_finish:\n      eating_speed_result = eating_speed_mid\n      right_speed = eating_speed_mid - 1\n\n    # Current eating speed is too slow\n    else:\n\n      left_speed = eating_speed_mid + 1\n\n  return eating_speed_result\n",
        "PHP": "<?php\n\nfunction canEatAllBananas(array $piles, int $eatingSpeed, int $maxTime): bool {\n    $totalTimeNeeded = 0;\n    foreach ($piles as $pileSize) {\n        $totalTimeNeeded += ceil($pileSize / $eatingSpeed);\n    }\n    return $totalTimeNeeded <= $maxTime;\n}\n\nfunction kokoEatingBananas(array $piles, int $maxTime): int {\n    $maximumPileSize = max($piles);\n    $minimumEatingSpeed = 1;\n    $maximumEatingSpeed = $maximumPileSize;\n\n    $optimalEatingSpeed = $maximumEatingSpeed;\n\n    while ($minimumEatingSpeed <= $maximumEatingSpeed) {\n        $currentEatingSpeed = $minimumEatingSpeed + floor(($maximumEatingSpeed - $minimumEatingSpeed) / 2);\n\n        // Check if Koko can eat all bananas at the current eating speed.\n        if (canEatAllBananas($piles, $currentEatingSpeed, $maxTime)) {\n            // If yes, try to find a smaller eating speed.\n            $optimalEatingSpeed = $currentEatingSpeed;\n            $maximumEatingSpeed = $currentEatingSpeed - 1;\n        } else {\n            // If not, increase the eating speed.\n            $minimumEatingSpeed = $currentEatingSpeed + 1;\n        }\n    }\n\n    return $optimalEatingSpeed;\n}\n\n?>"
      }
    }
  }
}
