{
  "id": "70665qlJEWMwRA5YaOUR",
  "slug": "median-of-two-sorted-arrays",
  "rank": 12,
  "title": "Median of Two Sorted Arrays",
  "difficulty": "hard",
  "topics": [
    "Binary Search"
  ],
  "externalUrl": "https://www.leetcode.com/problems/median-of-two-sorted-arrays",
  "numViews": 1234,
  "questionBody": "<p>Given two sorted arrays <code>nums1</code> and <code>nums2</code> of size <code>m</code> and <code>n</code> respectively, return <strong>the median</strong> of the two sorted arrays.</p>\n\n<p>The overall run time complexity should be <code>O(log (m+n))</code>.</p>\n\n<p>&nbsp;</p>\n<p><strong class=\"example\">Example 1:</strong></p>\n\n<pre>\n<strong>Input:</strong> nums1 = [1,3], nums2 = [2]\n<strong>Output:</strong> 2.00000\n<strong>Explanation:</strong> merged array = [1,2,3] and median is 2.\n</pre>\n\n<p><strong class=\"example\">Example 2:</strong></p>\n\n<pre>\n<strong>Input:</strong> nums1 = [1,2], nums2 = [3,4]\n<strong>Output:</strong> 2.50000\n<strong>Explanation:</strong> merged array = [1,2,3,4] and median is (2 + 3) / 2 = 2.5.\n</pre>\n\n<p>&nbsp;</p>\n<p><strong>Constraints:</strong></p>\n\n<ul>\n\t<li><code>nums1.length == m</code></li>\n\t<li><code>nums2.length == n</code></li>\n\t<li><code>0 &lt;= m &lt;= 1000</code></li>\n\t<li><code>0 &lt;= n &lt;= 1000</code></li>\n\t<li><code>1 &lt;= m + n &lt;= 2000</code></li>\n\t<li><code>-10<sup>6</sup> &lt;= nums1[i], nums2[i] &lt;= 10<sup>6</sup></code></li>\n</ul>\n",
  "clarifyingQuestions": [
    "Can the input arrays, nums1 and nums2, be empty, and if so, how should I handle that case?",
    "What is the expected data type of the numbers in the arrays? Are they integers, floating-point numbers, or some other numeric type?",
    "What is the range of possible values for the numbers in the input arrays? Are negative values allowed?",
    "In the case of an even combined length of the two arrays, should the median be the average of the two middle elements, and should I round the result if it's a float?",
    "Are duplicate numbers allowed within the input arrays, and if so, how should they be handled when determining the median?"
  ],
  "edgeCases": [
    {
      "edgeCase": "Both arrays are empty",
      "handling": "Return an appropriate error value or throw an exception, as the median is undefined for empty arrays."
    },
    {
      "edgeCase": "One array is empty, the other is not",
      "handling": "The median is simply the median of the non-empty array, which can be calculated directly."
    },
    {
      "edgeCase": "Arrays of size 1 and size > 1",
      "handling": "The algorithm should correctly merge a very small array with a significantly larger one and identify the median element(s)."
    },
    {
      "edgeCase": "Arrays contain duplicate numbers",
      "handling": "The binary search partitioning logic should correctly handle duplicates without entering infinite loops or miscalculating the median."
    },
    {
      "edgeCase": "Arrays contain negative numbers, zero, and positive numbers",
      "handling": "The comparison logic should work correctly for all number types including negative numbers and zero."
    },
    {
      "edgeCase": "Arrays with large numbers that may cause integer overflow during calculations (e.g., sums)",
      "handling": "Ensure that the calculations used for the median (especially when averaging two values) are performed using a data type that can accommodate large numbers, such as long or double, to avoid overflow."
    },
    {
      "edgeCase": "Arrays with all identical values",
      "handling": "Binary search must handle identical values within the array without getting stuck in an infinite loop."
    },
    {
      "edgeCase": "Arrays are highly skewed (e.g., one array has very small values and the other has very large values)",
      "handling": "Binary search should still converge to the correct partition even with disparate value ranges."
    }
  ],
  "companies": [
    {
      "slug": "amazon",
      "name": "Amazon",
      "logo": "/logos/amazon.jpg"
    },
    {
      "slug": "google",
      "name": "Google",
      "logo": "/logos/google.jpg"
    },
    {
      "slug": "microsoft",
      "name": "Microsoft",
      "logo": "/logos/microsoft.jpg"
    },
    {
      "slug": "bloomberg-lp",
      "name": "Bloomberg",
      "logo": "/logos/bloomberg-lp.jpg"
    },
    {
      "slug": "meta",
      "name": "Meta",
      "logo": "/logos/meta.jpg"
    },
    {
      "slug": "yahoo",
      "name": "Yahoo",
      "logo": "/logos/yahoo.jpg"
    },
    {
      "slug": "apple",
      "name": "Apple",
      "logo": "/logos/apple.jpg"
    },
    {
      "slug": "adobe",
      "name": "Adobe",
      "logo": "/logos/adobe.jpg"
    },
    {
      "slug": "uber",
      "name": "Uber",
      "logo": "/logos/uber.jpg"
    },
    {
      "slug": "goldman-sachs",
      "name": "Goldman Sachs",
      "logo": "/logos/goldman-sachs.jpg"
    },
    {
      "slug": "snap",
      "name": "Snap",
      "logo": "/logos/snap.png"
    },
    {
      "slug": "tiktok",
      "name": "TikTok",
      "logo": "/logos/tiktok.png"
    },
    {
      "slug": "citadel",
      "name": "Citadel",
      "logo": "/logos/citadel.jpg"
    },
    {
      "slug": "dropbox",
      "name": "Dropbox",
      "logo": "/logos/dropbox.jpg"
    },
    {
      "slug": "rippling",
      "name": "Rippling",
      "logo": "/logos/rippling.jpg"
    },
    {
      "slug": "walmart",
      "name": "Walmart",
      "logo": "/logos/walmart.jpg"
    },
    {
      "slug": "oracle",
      "name": "Oracle",
      "logo": "/logos/oracle.jpg"
    },
    {
      "slug": "autodesk",
      "name": "Autodesk",
      "logo": "/logos/autodesk.jpg"
    },
    {
      "slug": "servicenow",
      "name": "ServiceNow",
      "logo": "/logos/servicenow.jpg"
    },
    {
      "slug": "salesforce",
      "name": "Salesforce",
      "logo": "/logos/salesforce.png"
    },
    {
      "slug": "ibm",
      "name": "IBM",
      "logo": "/logos/ibm.jpg"
    },
    {
      "slug": "linkedin",
      "name": "LinkedIn",
      "logo": "/logos/linkedin.png"
    },
    {
      "slug": "paypal",
      "name": "PayPal",
      "logo": "/logos/paypal.jpg"
    },
    {
      "slug": "intuit",
      "name": "Intuit",
      "logo": "/logos/intuit.jpg"
    },
    {
      "slug": "flipkart",
      "name": "Flipkart",
      "logo": "/logos/flipkart.jpg"
    },
    {
      "slug": "capgemini",
      "name": "Capgemini",
      "logo": "/logos/capgemini.jpg"
    },
    {
      "slug": "swiggy",
      "name": "Swiggy",
      "logo": "/logos/swiggy.jpg"
    },
    {
      "slug": "de-shaw",
      "name": "De Shaw",
      "logo": "/logos/de-shaw.jpg"
    },
    {
      "slug": "okta",
      "name": "Okta",
      "logo": "/logos/okta.jpg"
    },
    {
      "slug": "visa",
      "name": "Visa",
      "logo": "/logos/visa.png"
    },
    {
      "slug": "palo-alto-networks",
      "name": "Palo Alto Networks",
      "logo": "/logos/palo-alto-networks.jpg"
    },
    {
      "slug": "blackrock",
      "name": "Blackrock",
      "logo": "/logos/blackrock.jpg"
    }
  ],
  "solutions": {
    "bruteForce": {
      "overview": "The brute force approach for finding the median combines two sorted lists and then finds the middle element. It's like merging two decks of cards and then picking the middle card. This approach doesn't try to be efficient; it just does the most obvious thing.",
      "steps": [
        "First, take all the numbers from both lists and put them into a single new list.",
        "Then, sort the combined list from smallest to largest.",
        "Next, find the middle of the sorted list. If the list has an odd number of elements, the middle element is the median.",
        "If the list has an even number of elements, the median is the average of the two elements in the middle."
      ],
      "bigO": {
        "runtimeValue": "O((n+m)log(n+m))",
        "runtimeExplanation": "The first step involves combining the two input arrays, nums1 and nums2, into a single array. If the lengths of nums1 and nums2 are n and m respectively, this takes O(n+m) time. The next step is sorting this combined array, which has a length of n+m. The time complexity of a typical sorting algorithm (like merge sort or quicksort, often used in built-in sort functions) is O(k log k) where k is the number of elements being sorted. In this case, k = n+m. Therefore, the sorting step takes O((n+m)log(n+m)) time. Finding the median after sorting takes constant time, O(1). The dominant operation is the sorting step, so the overall time complexity is O((n+m)log(n+m)).",
        "spaceValue": "O(N)",
        "spaceExplanation": "The brute force approach described creates a new list to store all elements from the two input arrays. If the total number of elements in the two input arrays is N, then the combined list will also have a size of N. Therefore, the algorithm requires auxiliary space proportional to the total number of elements from the inputs. This results in a space complexity of O(N)."
      },
      "languages": [
        "Python",
        "JavaScript",
        "TypeScript",
        "Java",
        "C++",
        "C#",
        "Go",
        "Rust",
        "Kotlin",
        "Swift",
        "Ruby",
        "PHP"
      ],
      "code": {
        "Python": "def find_median_sorted_arrays_brute_force(first_array, second_array):\n    # Combine the two input arrays into a single array\n    combined_array = first_array + second_array\n\n    # Sort the combined array\n    combined_array.sort()\n\n    combined_array_length = len(combined_array)\n\n    # Determine if the array has an even or odd number of elements\n    if combined_array_length % 2 == 0:\n        # Calculate indices of the two middle elements for even length array\n        middle_index_one = combined_array_length // 2 - 1\n        middle_index_two = combined_array_length // 2\n\n        #  Calculate the median as average of the two middle elements\n        median = (combined_array[middle_index_one] + combined_array[middle_index_two]) / 2\n\n    else:\n        # Calculate the index of the middle element for odd length array\n        middle_index = combined_array_length // 2\n\n        # Median is simply the middle element\n        median = combined_array[middle_index]\n\n    return median",
        "JavaScript": "function findMedianSortedArraysBruteForce(firstArray, secondArray) {\n\n  const combinedArray = firstArray.concat(secondArray);\n\n  // Sort the combined array to easily find the median\n  combinedArray.sort((firstNumber, secondNumber) => firstNumber - secondNumber);\n\n  const combinedArrayLength = combinedArray.length;\n\n  // Handle the even number of elements case.\n  if (combinedArrayLength % 2 === 0) {\n\n    const middleIndexOne = combinedArrayLength / 2 - 1;\n    const middleIndexTwo = combinedArrayLength / 2;\n\n    // Average the two middle numbers to get the median.\n    const median = (combinedArray[middleIndexOne] + combinedArray[middleIndexTwo]) / 2;\n    return median;\n  } else {\n\n    // Return the middle element for odd length arrays.\n    const middleIndex = Math.floor(combinedArrayLength / 2);\n    return combinedArray[middleIndex];\n  }\n}",
        "TypeScript": "function findMedianSortedArraysBruteForce(firstArray: number[], secondArray: number[]): number {\n  const combinedArray: number[] = firstArray.concat(secondArray);\n\n  // Sort the combined array to easily find the median.\n  combinedArray.sort((firstNumber, secondNumber) => firstNumber - secondNumber);\n\n  const combinedArrayLength: number = combinedArray.length;\n  \n  //Check if the array length is even or odd.\n  if (combinedArrayLength % 2 === 0) {\n\n    const middleIndex: number = combinedArrayLength / 2;\n\n    // Calculate the average of the two middle elements.\n    const sumOfMiddleElements: number = combinedArray[middleIndex - 1] + combinedArray[middleIndex];\n\n    return sumOfMiddleElements / 2;\n  } else {\n\n    // Directly return the middle element.\n    return combinedArray[Math.floor(combinedArrayLength / 2)];\n  }\n}",
        "Java": "class Solution {\n\n    public double findMedianSortedArrays(int[] nums1, int[] nums2) {\n        int combinedArrayLength = nums1.length + nums2.length;\n        int[] combinedArray = new int[combinedArrayLength];\n\n        // Copy elements from both arrays into the combined array\n        System.arraycopy(nums1, 0, combinedArray, 0, nums1.length);\n        System.arraycopy(nums2, 0, combinedArray, nums1.length, nums2.length);\n\n        java.util.Arrays.sort(combinedArray);\n\n        // Determine if the combined array length is even or odd\n        if (combinedArrayLength % 2 == 0) {\n            // If even, average the two middle elements\n            int middleIndex2 = combinedArrayLength / 2;\n            int middleIndex1 = middleIndex2 - 1;\n\n            return (double) (combinedArray[middleIndex1] + combinedArray[middleIndex2]) / 2;\n\n        } else {\n            // If odd, return the single middle element\n            int middleIndex = combinedArrayLength / 2;\n            return (double) combinedArray[middleIndex];\n        }\n    }\n}",
        "C++": "#include <vector>\n#include <algorithm>\n\ndouble findMedianSortedArraysBruteForce(std::vector<int>& firstArray, std::vector<int>& secondArray) {\n    std::vector<int> mergedArray;\n\n    // Combine both arrays into a single array\n    mergedArray.insert(mergedArray.end(), firstArray.begin(), firstArray.end());\n    mergedArray.insert(mergedArray.end(), secondArray.begin(), secondArray.end());\n\n    // Sort the combined array to easily find the median\n    std::sort(mergedArray.begin(), mergedArray.end());\n\n    int mergedArraySize = mergedArray.size();\n\n    // Handle even number of elements case to find the average of the middle two\n    if (mergedArraySize % 2 == 0) {\n        int middleIndex = mergedArraySize / 2;\n        double sumOfMiddleElements = mergedArray[middleIndex - 1] + mergedArray[middleIndex];\n\n        return sumOfMiddleElements / 2.0;\n    }\n\n    // For odd number of elements, just return the middle element\n    else {\n        return mergedArray[mergedArraySize / 2];\n    }\n}",
        "C#": "public class Solution\n{\n    public double FindMedianSortedArrays(int[] nums1, int[] nums2)\n    {\n        int totalLength = nums1.Length + nums2.Length;\n        int[] mergedArray = new int[totalLength];\n\n        // Combine the two arrays into one.\n        Array.Copy(nums1, mergedArray, nums1.Length);\n        Array.Copy(nums2, 0, mergedArray, nums1.Length, nums2.Length);\n\n        // Sort the combined array to easily find the median.\n        Array.Sort(mergedArray);\n\n        if (totalLength % 2 == 0)\n        {\n            // Even number of elements.\n            // Need to average the two middle elements.\n\n            double middleElement1 = mergedArray[totalLength / 2 - 1];\n            double middleElement2 = mergedArray[totalLength / 2];\n\n            return (middleElement1 + middleElement2) / 2.0;\n        }\n        else\n        {\n            // Odd number of elements.\n            // The median is simply the middle element.\n\n            return mergedArray[totalLength / 2];\n        }\n    }\n}",
        "Go": "package main\n\nimport \"sort\"\n\nfunc findMedianSortedArraysBruteForce(firstArray []int, secondArray []int) float64 {\n\tcombinedArray := append(firstArray, secondArray...)\n\n\t// Sort the combined array so we can easily find the median\n\tsort.Ints(combinedArray)\n\tarrayLength := len(combinedArray)\n\n\t// Handle the case where the combined array is empty\n\tif arrayLength == 0 {\n\t\treturn 0.0\n\t}\n\n\t// Determine if the combined array has an even or odd number of elements.\n\tif arrayLength%2 == 0 {\n\t\tmiddleRightIndex := arrayLength / 2\n\t\tmiddleLeftIndex := middleRightIndex - 1\n\n\t\t// If even, average the two middle elements.\n\t\treturn float64(combinedArray[middleLeftIndex]+combinedArray[middleRightIndex]) / 2.0\n\t}\n\n\t// If odd, simply return the middle element.\n\tmiddleIndex := arrayLength / 2\n\treturn float64(combinedArray[middleIndex])\n}",
        "Rust": "fn find_median_brute_force(first_array: Vec<i32>, second_array: Vec<i32>) -> f64 {\n    let mut combined_array: Vec<i32> = Vec::new();\n\n    // Combine the two input arrays into one\n    combined_array.extend(first_array);\n    combined_array.extend(second_array);\n\n    // Sort the combined array\n    combined_array.sort();\n\n    let combined_array_length = combined_array.len();\n\n    // Different calculation for odd vs even sized array\n    if combined_array_length % 2 == 0 {\n\n        //Calculate the mean of two middle numbers\n        let middle_index_one = (combined_array_length / 2) - 1;\n        let middle_index_two = combined_array_length / 2;\n        let sum_of_middle_elements = combined_array[middle_index_one] as f64 + combined_array[middle_index_two] as f64;\n        sum_of_middle_elements / 2.0\n    } else {\n        // For odd length, simply return middle element.\n        let middle_index = combined_array_length / 2;\n        combined_array[middle_index] as f64\n    }\n}",
        "Kotlin": "fun findMedianSortedArraysBruteForce(firstArray: IntArray, secondArray: IntArray): Double {\n    // Combine the two input arrays into a single array.\n    val combinedArray = firstArray + secondArray\n\n    // Sort the combined array in ascending order.\n    combinedArray.sort()\n\n    val combinedArrayLength = combinedArray.size\n\n    //Calculate the middle index to determine median.\n    val middleIndex = combinedArrayLength / 2\n\n    if (combinedArrayLength % 2 == 0) {\n        //Even length, so average the two middle elements.\n\n        val firstMiddleElement = combinedArray[middleIndex - 1]\n\n        val secondMiddleElement = combinedArray[middleIndex]\n\n        return (firstMiddleElement + secondMiddleElement) / 2.0\n\n    } else {\n        // Odd length, so return the middle element.\n        return combinedArray[middleIndex].toDouble()\n    }\n}",
        "Swift": "func findMedianBruteForce(firstArray: [Int], secondArray: [Int]) -> Double {\n\n    let combinedArray = firstArray + secondArray\n\n    let sortedCombinedArray = combinedArray.sorted()\n\n    let combinedArrayLength = sortedCombinedArray.count\n\n    // Handle the case where the array has an odd number of elements.\n    if combinedArrayLength % 2 != 0 {\n\n        let middleIndex = combinedArrayLength / 2\n        return Double(sortedCombinedArray[middleIndex])\n    }\n\n    // Handle the case where the array has an even number of elements.\n    else {\n\n        let middleIndexTwo = combinedArrayLength / 2\n        let middleIndexOne = middleIndexTwo - 1\n\n        // Calculate the average of the two middle elements.\n        let sumOfMiddleElements = sortedCombinedArray[middleIndexOne] + sortedCombinedArray[middleIndexTwo]\n\n        return Double(sumOfMiddleElements) / 2.0\n    }\n}",
        "Ruby": "def find_median_brute_force(first_array, second_array)\n  combined_array = first_array + second_array\n\n  # Sorting is required to easily find the median\n  sorted_array = combined_array.sort\n\n  array_length = sorted_array.length\n\n  # Different logic based on even or odd length\n  if array_length % 2 == 0\n\n    middle_index_two = array_length / 2\n    middle_index_one = middle_index_two - 1\n\n    sum_of_middle = sorted_array[middle_index_one] + sorted_array[middle_index_two]\n    median = sum_of_middle.to_f / 2\n  \n    return median\n\n  else\n    middle_index = array_length / 2\n\n    # Integer division gives the correct index\n    median = sorted_array[middle_index]\n\n    return median\n  end\nend",
        "PHP": "<?php\n\nfunction findMedianSortedArraysBruteForce(array $firstArray, array $secondArray): float\n{\n    // Combine the two arrays into one.\n    $combinedArray = array_merge($firstArray, $secondArray);\n\n    // Sort the combined array.\n    sort($combinedArray);\n\n    $combinedArrayLength = count($combinedArray);\n\n    // Determine if the length is even or odd to calculate the median.\n    if ($combinedArrayLength % 2 == 0) {\n        // If even, average the two middle elements.\n\n        $middleRightIndex = $combinedArrayLength / 2;\n\n        $middleLeftIndex = $middleRightIndex - 1;\n\n        $median = ($combinedArray[$middleLeftIndex] + $combinedArray[$middleRightIndex]) / 2;\n\n    } else {\n        //If odd, the median is the middle element.\n        $middleIndex = floor($combinedArrayLength / 2);\n        $median = $combinedArray[$middleIndex];\n\n    }\n    return $median;\n}\n\n?>"
      }
    },
    "optimal": {
      "overview": "The fastest way to find the middle value of two sorted lists combined is to efficiently narrow down the search area. We strategically eliminate halves of the lists that cannot contain the median, similar to a guessing game where you adjust your range with each guess.",
      "steps": [
        "First, figure out which list is shorter, and focus on that list.",
        "Imagine dividing the shorter list into two parts. We're trying to find the perfect dividing point.",
        "If we make a cut in the shorter list, we can figure out where to make a corresponding cut in the longer list to ensure we have the same number of elements on either side of both cuts.",
        "Now, check if the elements near the cuts are in the correct order. Specifically, is the largest value on the left side of the cut smaller than the smallest value on the right side of the cut? If so, we've found the right cuts.",
        "If not, adjust the cut in the shorter list and repeat the process. If the values are too big on the left, move the cut to the left. If the values are too small, move the cut to the right.",
        "Once the perfect cuts are found, the median can be easily calculated from the values closest to those cuts. It might be the average of two numbers if we have an even number of total elements, or simply one number if we have an odd number of elements."
      ],
      "bigO": {
        "runtimeValue": "O(log(min(m, n)))",
        "runtimeExplanation": "The algorithm performs a binary search on the shorter of the two arrays. Let m and n represent the lengths of the two arrays. In each step of the binary search, the search space is halved. The cost is driven by the binary search on the shorter array which results in log(min(m, n)) iterations. Therefore, the time complexity is O(log(min(m, n))). ",
        "spaceValue": "O(1)",
        "spaceExplanation": "The provided algorithm iteratively narrows down the search range using comparisons and adjustments of cut points (index variables). It does not create any auxiliary data structures like lists, arrays, or hash maps to store intermediate results or track visited elements. The operations involve only a few integer variables to keep track of the cut positions. Therefore, the auxiliary space used is constant and independent of the input size, resulting in O(1) space complexity."
      },
      "languages": [
        "Python",
        "JavaScript",
        "TypeScript",
        "Java",
        "C++",
        "C#",
        "Go",
        "Rust",
        "Kotlin",
        "Swift",
        "Ruby",
        "PHP"
      ],
      "code": {
        "Python": "def find_median_sorted_arrays(first_array, second_array):\n    if len(first_array) > len(second_array):\n        first_array, second_array = second_array, first_array\n\n    array_x_length = len(first_array)\n    array_y_length = len(second_array)\n\n    low_index = 0\n    high_index = array_x_length\n\n    while low_index <= high_index:\n        partition_x = (low_index + high_index) // 2\n\n        # Calculate partition of the second array\n        partition_y = (array_x_length + array_y_length + 1) // 2 - partition_x\n\n        max_left_x = first_array[partition_x - 1] if partition_x > 0 else float('-inf')\n        min_right_x = first_array[partition_x] if partition_x < array_x_length else float('inf')\n\n        max_left_y = second_array[partition_y - 1] if partition_y > 0 else float('-inf')\n        min_right_y = second_array[partition_y] if partition_y < array_y_length else float('inf')\n\n        # Check if partitions are correct\n        if max_left_x <= min_right_y and max_left_y <= min_right_x:\n\n            # We found the correct partition\n            if (array_x_length + array_y_length) % 2 == 0:\n                return (max(max_left_x, max_left_y) + min(min_right_x, min_right_y)) / 2\n            else:\n                return max(max_left_x, max_left_y)\n\n        # Adjust partitions based on comparisons\n        elif max_left_x > min_right_y:\n            # Move towards left in first_array\n            high_index = partition_x - 1\n        else:\n            # Move towards right in first_array\n            low_index = partition_x + 1\n\n    return None # Should never reach here, input arrays are sorted",
        "JavaScript": "function findMedianSortedArrays(nums1, nums2) {\n  if (nums1.length > nums2.length) {\n    return findMedianSortedArrays(nums2, nums1);\n  }\n\n  const arrayXLength = nums1.length;\n  const arrayYLength = nums2.length;\n  let low = 0;\n  let high = arrayXLength;\n\n  while (low <= high) {\n    const partitionX = Math.floor((low + high) / 2);\n    const partitionY = Math.floor((arrayXLength + arrayYLength + 1) / 2) - partitionX;\n\n    const maxX = partitionX === 0 ? -Infinity : nums1[partitionX - 1];\n    const minX = partitionX === arrayXLength ? Infinity : nums1[partitionX];\n\n    const maxY = partitionY === 0 ? -Infinity : nums2[partitionY - 1];\n    const minY = partitionY === arrayYLength ? Infinity : nums2[partitionY];\n\n    // Check if the partitions are correct.\n    if (maxX <= minY && maxY <= minX) {\n      // We have found the correct partition.\n      if ((arrayXLength + arrayYLength) % 2 === 0) {\n        return (Math.max(maxX, maxY) + Math.min(minX, minY)) / 2;\n      } else {\n        return Math.max(maxX, maxY);\n      }\n    } else if (maxX > minY) {\n      // We need to move towards the left in arrayX.\n      high = partitionX - 1;\n    } else {\n      // We need to move towards the right in arrayX.\n      low = partitionX + 1;\n    }\n  }\n}",
        "TypeScript": "function findMedianSortedArrays(nums1: number[], nums2: number[]): number {\n    if (nums1.length > nums2.length) {\n      return findMedianSortedArrays(nums2, nums1);\n    }\n\n    const arrayXLength = nums1.length;\n    const arrayYLength = nums2.length;\n    let low = 0;\n    let high = arrayXLength;\n\n    while (low <= high) {\n      const partitionX = Math.floor((low + high) / 2);\n      const partitionY = Math.floor((arrayXLength + arrayYLength + 1) / 2) - partitionX;\n\n      const maxX = partitionX === 0 ? -Infinity : nums1[partitionX - 1];\n      const minX = partitionX === arrayXLength ? Infinity : nums1[partitionX];\n\n      const maxY = partitionY === 0 ? -Infinity : nums2[partitionY - 1];\n      const minY = partitionY === arrayYLength ? Infinity : nums2[partitionY];\n\n      // Check if the partitions are correct.\n      if (maxX <= minY && maxY <= minX) {\n\n        // If combined array is even in length.\n        if ((arrayXLength + arrayYLength) % 2 === 0) {\n          return (Math.max(maxX, maxY) + Math.min(minX, minY)) / 2;\n        } else {\n          // If combined array is odd in length.\n          return Math.max(maxX, maxY);\n        }\n      } else if (maxX > minY) {\n        // Need to move towards left in nums1.\n        high = partitionX - 1;\n      } else {\n\n        // Need to move towards right in nums1.\n        low = partitionX + 1;\n      }\n    }\n\n    return 0;\n  }",
        "Java": "public class Solution {\n    public double findMedianSortedArrays(int[] nums1, int[] nums2) {\n        if (nums1.length > nums2.length) {\n            return findMedianSortedArrays(nums2, nums1);\n        }\n\n        int arrayOneLength = nums1.length;\n        int arrayTwoLength = nums2.length;\n        int low = 0;\n        int high = arrayOneLength;\n\n        while (low <= high) {\n            int partitionArrayOne = (low + high) / 2;\n\n            // Calculate partitionArrayTwo to maintain equal halves\n            int partitionArrayTwo = (arrayOneLength + arrayTwoLength + 1) / 2 - partitionArrayOne;\n\n            int maxLeftArrayOne = (partitionArrayOne == 0) ? Integer.MIN_VALUE : nums1[partitionArrayOne - 1];\n            int minRightArrayOne = (partitionArrayOne == arrayOneLength) ? Integer.MAX_VALUE : nums1[partitionArrayOne];\n\n            int maxLeftArrayTwo = (partitionArrayTwo == 0) ? Integer.MIN_VALUE : nums2[partitionArrayTwo - 1];\n            int minRightArrayTwo = (partitionArrayTwo == arrayTwoLength) ? Integer.MAX_VALUE : nums2[partitionArrayTwo];\n\n            // We have found the correct partition\n            if (maxLeftArrayOne <= minRightArrayTwo && maxLeftArrayTwo <= minRightArrayOne) {\n\n                if ((arrayOneLength + arrayTwoLength) % 2 == 0) {\n                    //Even number of elements\n                    return (Math.max(maxLeftArrayOne, maxLeftArrayTwo) + Math.min(minRightArrayOne, minRightArrayTwo)) / 2.0;\n                } else {\n\n                    //Odd number of elements\n                    return Math.max(maxLeftArrayOne, maxLeftArrayTwo);\n                }\n            } else if (maxLeftArrayOne > minRightArrayTwo) {\n\n                // Move towards left in arrayOne\n                high = partitionArrayOne - 1;\n\n            } else {\n\n                // Move towards right in arrayOne\n                low = partitionArrayOne + 1;\n            }\n        }\n\n        return 0.0; \n    }\n}",
        "C++": "#include <algorithm>\n\nusing namespace std;\n\ndouble findMedianSortedArrays(int input_array_one[], int array_one_size, int input_array_two[], int array_two_size) {\n    // Ensure array_one is the shorter array.\n    if (array_one_size > array_two_size) {\n        return findMedianSortedArrays(input_array_two, array_two_size, input_array_one, array_one_size);\n    }\n\n    int shorter_array_size = array_one_size;\n    int longer_array_size = array_two_size;\n    int low = 0;\n    int high = shorter_array_size;\n\n    while (low <= high) {\n        int partition_x = (low + high) / 2;\n\n        // Calculate partition_y based on sizes and partition_x.\n        int partition_y = (shorter_array_size + longer_array_size + 1) / 2 - partition_x;\n\n        // Determine maxLeftX, minRightX, maxLeftY, and minRightY.\n        int max_left_x = (partition_x == 0) ? -2147483648 : input_array_one[partition_x - 1];\n        int min_right_x = (partition_x == shorter_array_size) ? 2147483647 : input_array_one[partition_x];\n\n        int max_left_y = (partition_y == 0) ? -2147483648 : input_array_two[partition_y - 1];\n        int min_right_y = (partition_y == longer_array_size) ? 2147483647 : input_array_two[partition_y];\n\n        // Check if the partitions are correct.\n        if (max_left_x <= min_right_y && max_left_y <= min_right_x) {\n            // If the combined array has an even number of elements.\n            if ((shorter_array_size + longer_array_size) % 2 == 0) {\n                return (double)(max(max_left_x, max_left_y) + min(min_right_x, min_right_y)) / 2;\n            } else {\n                // If the combined array has an odd number of elements.\n                return (double)max(max_left_x, max_left_y);\n            }\n        } else if (max_left_x > min_right_y) {\n            // Move towards left in array_one.\n            high = partition_x - 1;\n\n        } else {\n            // Move towards right in array_one.\n            low = partition_x + 1;\n        }\n    }\n\n    return 0.0;\n}\n\ndouble findMedian(int input_array_one[], int array_one_size, int input_array_two[], int array_two_size) {\n    return findMedianSortedArrays(input_array_one, array_one_size, input_array_two, array_two_size);\n}",
        "C#": "using System;\n\npublic class Solution\n{\n    public double FindMedianSortedArrays(int[] nums1, int[] nums2)\n    {\n        if (nums1.Length > nums2.Length)\n        {\n            return FindMedianSortedArrays(nums2, nums1);\n        }\n\n        int totalLength = nums1.Length + nums2.Length;\n        int partitionX = 0;\n        int partitionY = 0;\n        int low = 0;\n        int high = nums1.Length;\n\n        while (low <= high)\n        {\n            partitionX = (low + high) / 2;\n            partitionY = (totalLength + 1) / 2 - partitionX;\n\n            double maxLeftX = (partitionX == 0) ? double.NegativeInfinity : nums1[partitionX - 1];\n            double minRightX = (partitionX == nums1.Length) ? double.PositiveInfinity : nums1[partitionX];\n\n            double maxLeftY = (partitionY == 0) ? double.NegativeInfinity : nums2[partitionY - 1];\n            double minRightY = (partitionY == nums2.Length) ? double.PositiveInfinity : nums2[partitionY];\n\n            // We found the right cuts, elements near cuts in correct order\n            if (maxLeftX <= minRightY && maxLeftY <= minRightX)\n            {\n                if (totalLength % 2 == 0)\n                {\n                    return (Math.Max(maxLeftX, maxLeftY) + Math.Min(minRightX, minRightY)) / 2.0;\n                }\n                else\n                {\n                    return Math.Max(maxLeftX, maxLeftY);\n                }\n            } else if (maxLeftX > minRightY)\n            {\n                // Adjust cut in shorter list, move cut to left\n                high = partitionX - 1;\n            } else\n            {\n                // Adjust cut in shorter list, move cut to right\n                low = partitionX + 1;\n            }\n        }\n\n        throw new ArgumentException(",
        "Go": "package main\n\nfunc findMedianSortedArrays(nums1 []int, nums2 []int) float64 {\n\tshortArray := nums1\n\tlongArray := nums2\n\tif len(nums2) < len(nums1) {\n\t\tshortArray = nums2\n\t\tlongArray = nums1\n\t}\n\n\tm := len(shortArray)\n\tn := len(longArray)\n\tlow := 0\n\thigh := m\n\n\tfor low <= high {\n\t\tpartitionShortArray := (low + high) / 2\n\t\tpartitionLongArray := (m+n+1)/2 - partitionShortArray\n\n\t\tmaxLeftShortArray := -10000000.0\n\t\tif partitionShortArray > 0 {\n\t\t\tmaxLeftShortArray = float64(shortArray[partitionShortArray-1])\n\t\t}\n\n\t\tminRightShortArray := 10000000.0\n\t\tif partitionShortArray < m {\n\t\t\tminRightShortArray = float64(shortArray[partitionShortArray])\n\t\t}\n\n\t\tmaxLeftLongArray := -10000000.0\n\t\tif partitionLongArray > 0 {\n\t\t\tmaxLeftLongArray = float64(longArray[partitionLongArray-1])\n\t\t}\n\n\t\tminRightLongArray := 10000000.0\n\t\tif partitionLongArray < n {\n\t\t\tminRightLongArray = float64(longArray[partitionLongArray])\n\t\t}\n\n\t\t// Check if the partition is correct.\n\t\tif maxLeftShortArray <= minRightLongArray && maxLeftLongArray <= minRightShortArray {\n\t\t\tif (m+n)%2 == 0 {\n\t\t\t\treturn float64(max(maxLeftShortArray, maxLeftLongArray)+min(minRightShortArray, minRightLongArray)) / 2.0\n\t\t\t} else {\n\t\t\t\treturn float64(max(maxLeftShortArray, maxLeftLongArray))\n\t\t\t}\n\t\t} else if maxLeftShortArray > minRightLongArray {\n\t\t\thigh = partitionShortArray - 1 // Move towards the left.\n\t\t} else {\n\t\t\tlow = partitionShortArray + 1 // Move towards the right.\n\t\t}\n\t}\n\n\treturn 0.0\n}\n\nfunc max(a float64, b float64) float64 {\n\tif a > b {\n\t\treturn a\n\t}\n\treturn b\n}\n\nfunc min(a float64, b float64) float64 {\n\tif a < b {\n\t\treturn a\n\t}\n\treturn b\n}",
        "Rust": "pub fn find_median_sorted_arrays(nums1: Vec<i32>, nums2: Vec<i32>) -> f64 {\n    let (shorter_list, longer_list) = if nums1.len() <= nums2.len() {\n        (nums1, nums2)\n    } else {\n        (nums2, nums1)\n    };\n\n    let total_length = shorter_list.len() + longer_list.len();\n    let mut low_index = 0;\n    let mut high_index = shorter_list.len();\n\n    while low_index <= high_index {\n        let partition_x = (low_index + high_index) / 2;\n        // Calculate partition of the longer list\n        let partition_y = (total_length + 1) / 2 - partition_x;\n\n        let max_left_x = if partition_x == 0 { i32::MIN } else { shorter_list[partition_x - 1] };\n        let min_right_x = if partition_x == shorter_list.len() { i32::MAX } else { shorter_list[partition_x] };\n\n        let max_left_y = if partition_y == 0 { i32::MIN } else { longer_list[partition_y - 1] };\n        let min_right_y = if partition_y == longer_list.len() { i32::MAX } else { longer_list[partition_y] };\n\n        if max_left_x <= min_right_y && max_left_y <= min_right_x {\n            // Found the correct partition\n            if total_length % 2 == 0 {\n                // Even number of elements\n                return (std::cmp::max(max_left_x, max_left_y) as f64 + std::cmp::min(min_right_x, min_right_y) as f64) / 2.0;\n            } else {\n                // Odd number of elements\n                return std::cmp::max(max_left_x, max_left_y) as f64;\n            }\n        } else if max_left_x > min_right_y {\n            // Move towards left in shorter list\n            high_index = partition_x - 1;\n        } else {\n            // Move towards right in shorter list\n            low_index = partition_x + 1;\n        }\n    }\n\n    0.0\n}",
        "Kotlin": "fun findMedianSortedArrays(nums1: IntArray, nums2: IntArray): Double {\n    val shortArray = if (nums1.size <= nums2.size) nums1 else nums2\n    val longArray = if (nums1.size <= nums2.size) nums2 else nums1\n    val shortArraySize = shortArray.size\n    val longArraySize = longArray.size\n    var low = 0\n    var high = shortArraySize\n\n    while (low <= high) {\n      val partitionShortArray = (low + high) / 2\n\n      // Calculate partition for the longer array\n      val partitionLongArray = (shortArraySize + longArraySize + 1) / 2 - partitionShortArray\n\n      // Get maxLeftShort and minRightShort\n      val maxLeftShort = if (partitionShortArray == 0) Int.MIN_VALUE else shortArray[partitionShortArray - 1]\n      val minRightShort = if (partitionShortArray == shortArraySize) Int.MAX_VALUE else shortArray[partitionShortArray]\n\n      // Get maxLeftLong and minRightLong\n      val maxLeftLong = if (partitionLongArray == 0) Int.MIN_VALUE else longArray[partitionLongArray - 1]\n      val minRightLong = if (partitionLongArray == longArraySize) Int.MAX_VALUE else longArray[partitionLongArray]\n\n      // Check if partition is correct\n      if (maxLeftShort <= minRightLong && maxLeftLong <= minRightShort) {\n\n        //We have found a valid partition\n        return if ((shortArraySize + longArraySize) % 2 == 0) {\n          (Math.max(maxLeftShort, maxLeftLong) + Math.min(minRightShort, minRightLong)) / 2.0\n        } else {\n          Math.max(maxLeftShort, maxLeftLong).toDouble()\n        }\n      } else if (maxLeftShort > minRightLong) {\n\n        // Need to move towards left in shortArray\n        high = partitionShortArray - 1\n      } else {\n\n        // Need to move towards right in shortArray\n        low = partitionShortArray + 1\n      }\n    }\n    return 0.0\n  }\n}",
        "Swift": "struct MedianCalculator {\n\n    static func findMedianSortedArrays(nums1: [Int], nums2: [Int]) -> Double {\n        let shorterArray = nums1.count <= nums2.count ? nums1 : nums2\n        let longerArray = nums1.count <= nums2.count ? nums2 : nums1\n        let totalLength = nums1.count + nums2.count\n        \n        var lowIndex = 0\n        var highIndex = shorterArray.count\n        \n        while lowIndex <= highIndex {\n            let partitionX = (lowIndex + highIndex) / 2\n\n            // Calculate partition in the longer array\n            let partitionY = (totalLength + 1) / 2 - partitionX\n            \n            let maxLeftX = partitionX == 0 ? -Double.infinity : Double(shorterArray[partitionX - 1])\n            let minRightX = partitionX == shorterArray.count ? Double.infinity : Double(shorterArray[partitionX])\n            \n            let maxLeftY = partitionY == 0 ? -Double.infinity : Double(longerArray[partitionY - 1])\n            let minRightY = partitionY == longerArray.count ? Double.infinity : Double(longerArray[partitionY])\n\n            // Check if the partition is correct\n            if maxLeftX <= minRightY && maxLeftY <= minRightX {\n\n                //Even number of total elements\n                if totalLength % 2 == 0 {\n                    return (max(maxLeftX, maxLeftY) + min(minRightX, minRightY)) / 2.0\n                } else {\n                    //Odd number of total elements\n                    return max(maxLeftX, maxLeftY)\n                }\n            } else if maxLeftX > minRightY {\n\n                // Move towards left in shorter array\n                highIndex = partitionX - 1\n            } else {\n\n                // Move towards right in shorter array\n                lowIndex = partitionX + 1\n            }\n        }\n        return 0.0\n    }\n}",
        "Ruby": "def find_median_sorted_arrays(nums1, nums2)\n  if nums1.length > nums2.length\n    nums1, nums2 = nums2, nums1\n  end\n\n  partition_x = 0\n  partition_y = 0\n  low = 0\n  high = nums1.length\n\n  while low <= high\n    partition_x = (low + high) / 2\n    partition_y = ((nums1.length + nums2.length + 1) / 2) - partition_x\n\n    max_left_x = (partition_x == 0) ? -Float::INFINITY : nums1[partition_x - 1]\n    min_right_x = (partition_x == nums1.length) ? Float::INFINITY : nums1[partition_x]\n\n    max_left_y = (partition_y == 0) ? -Float::INFINITY : nums2[partition_y - 1]\n    min_right_y = (partition_y == nums2.length) ? Float::INFINITY : nums2[partition_y]\n\n    if max_left_x <= min_right_y && max_left_y <= min_right_x\n      # We have found the correct partition.\n      if (nums1.length + nums2.length) % 2 == 0\n        return (([max_left_x, max_left_y].max + [min_right_x, min_right_y].min).to_f) / 2\n      else\n        return [max_left_x, max_left_y].max.to_f\n      end\n    elsif max_left_x > min_right_y\n      # Need to move towards the left in nums1\n\n      high = partition_x - 1\n    else\n      # Need to move towards the right in nums1\n\n      low = partition_x + 1\n    end\n  end\nend\n\n# Ensure the shorter array is always nums1\ndef median_sorted_arrays(nums1, nums2)\n  find_median_sorted_arrays(nums1, nums2)\nend\n",
        "PHP": "<?php\nfunction findMedianSortedArrays(array $firstArray, array $secondArray): float {\n    $firstArrayLength = count($firstArray);\n    $secondArrayLength = count($secondArray);\n\n    // Ensure $firstArray is the shorter array.\n    if ($firstArrayLength > $secondArrayLength) {\n        return findMedianSortedArrays($secondArray, $firstArray);\n    }\n\n    $low = 0;\n    $high = $firstArrayLength;\n\n    while ($low <= $high) {\n        // Binary search on the shorter array.\n        $partitionFirstArray = (int)(($low + $high) / 2);\n        $partitionSecondArray = (int)(($firstArrayLength + $secondArrayLength + 1) / 2) - $partitionFirstArray;\n\n        $maxLeftFirstArray = ($partitionFirstArray == 0) ? PHP_FLOAT_MIN : $firstArray[$partitionFirstArray - 1];\n        $minRightFirstArray = ($partitionFirstArray == $firstArrayLength) ? PHP_FLOAT_MAX : $firstArray[$partitionFirstArray];\n\n        $maxLeftSecondArray = ($partitionSecondArray == 0) ? PHP_FLOAT_MIN : $secondArray[$partitionSecondArray - 1];\n        $minRightSecondArray = ($partitionSecondArray == $secondArrayLength) ? PHP_FLOAT_MAX : $secondArray[$partitionSecondArray];\n\n        // Check if the partitions are correct.\n        if ($maxLeftFirstArray <= $minRightSecondArray && $maxLeftSecondArray <= $minRightFirstArray) {\n            // We have found the correct partition.\n            if (($firstArrayLength + $secondArrayLength) % 2 == 0) {\n                // Even number of elements.\n                return (float)((max($maxLeftFirstArray, $maxLeftSecondArray) + min($minRightFirstArray, $minRightSecondArray)) / 2);\n            } else {\n                // Odd number of elements.\n                return (float)max($maxLeftFirstArray, $maxLeftSecondArray);\n            }\n        } elseif ($maxLeftFirstArray > $minRightSecondArray) {\n            // Move towards left in first array.\n            $high = $partitionFirstArray - 1;\n        } else {\n            // Move towards right in first array.\n            $low = $partitionFirstArray + 1;\n        }\n    }\n\n    return 0.0;\n}\n?>"
      }
    }
  }
}
